LICENSE
MANIFEST.in
README.md
modulefinder.py
setup.py
modulefinder.egg-info/PKG-INFO
modulefinder.egg-info/SOURCES.txt
modulefinder.egg-info/dependency_links.txt
modulefinder.egg-info/requires.txt
modulefinder.egg-info/top_level.txt
src/__init__.py
src/bioquali.py
src/sif_parser.py