Metadata-Version: 1.0
Name: modulefinder
Version: 0.2
Summary: A module finder.
Home-page: http://bioasp.github.io/modulefinder/
Author: Sven Thiele
Author-email: sthiele78@gmail.com
License: GPLv3+
Platform: UNKNOWN
